{"weekday": [{"station": "PSS1021", "arrivalTime": "", "departureTime": "10:12:24", "direction": "사상"}, {"station": "PSS1020", "arrivalTime": "10:14:21", "departureTime": "10:14:46", "direction": "사상"}, {"station": "PSS1019", "arrivalTime": "10:17:21", "departureTime": "10:17:46", "direction": "사상"}, {"station": "PSS1018", "arrivalTime": "10:19:14", "departureTime": "10:19:39", "direction": "사상"}, {"station": "PSS1017", "arrivalTime": "10:20:48", "departureTime": "10:21:13", "direction": "사상"}, {"station": "PSS1016", "arrivalTime": "10:22:13", "departureTime": "10:22:38", "direction": "사상"}, {"station": "PSS1015", "arrivalTime": "10:24:08", "departureTime": "10:24:33", "direction": "사상"}, {"station": "PSS1014", "arrivalTime": "10:25:30", "departureTime": "10:25:55", "direction": "사상"}, {"station": "PSS1013", "arrivalTime": "10:27:15", "departureTime": "10:27:40", "direction": "사상"}, {"station": "PSS1012", "arrivalTime": "10:29:12", "departureTime": "10:29:37", "direction": "사상"}, {"station": "PSS1011", "arrivalTime": "10:30:45", "departureTime": "10:31:10", "direction": "사상"}, {"station": "PSS1010", "arrivalTime": "10:32:18", "departureTime": "10:32:38", "direction": "사상"}, {"station": "PSS1009", "arrivalTime": "10:34:07", "departureTime": "10:34:27", "direction": "사상"}, {"station": "PSS1008", "arrivalTime": "10:36:02", "departureTime": "10:36:22", "direction": "사상"}, {"station": "PSS1007", "arrivalTime": "10:37:41", "departureTime": "10:38:11", "direction": "사상"}, {"station": "PSS1006", "arrivalTime": "10:40:42", "departureTime": "10:41:02", "direction": "사상"}, {"station": "PSS1005", "arrivalTime": "10:43:16", "departureTime": "10:43:41", "direction": "사상"}, {"station": "PSS1004", "arrivalTime": "10:45:45", "departureTime": "10:46:20", "direction": "사상"}, {"station": "PSS1003", "arrivalTime": "10:47:53", "departureTime": "10:48:18", "direction": "사상"}, {"station": "PSS1002", "arrivalTime": "10:50:57", "departureTime": "10:51:22", "direction": "사상"}, {"station": "PSS1001", "arrivalTime": "10:52:52", "departureTime": "", "direction": "사상"}]}