{"saturday": [{"station": "PSS1021", "arrivalTime": "", "departureTime": "12:54:42", "direction": "사상"}, {"station": "PSS1020", "arrivalTime": "12:56:39", "departureTime": "12:57:04", "direction": "사상"}, {"station": "PSS1019", "arrivalTime": "12:59:39", "departureTime": "13:00:04", "direction": "사상"}, {"station": "PSS1018", "arrivalTime": "13:01:32", "departureTime": "13:01:57", "direction": "사상"}, {"station": "PSS1017", "arrivalTime": "13:03:06", "departureTime": "13:03:31", "direction": "사상"}, {"station": "PSS1016", "arrivalTime": "13:04:31", "departureTime": "13:04:56", "direction": "사상"}, {"station": "PSS1015", "arrivalTime": "13:06:26", "departureTime": "13:06:51", "direction": "사상"}, {"station": "PSS1014", "arrivalTime": "13:07:48", "departureTime": "13:08:13", "direction": "사상"}, {"station": "PSS1013", "arrivalTime": "13:09:33", "departureTime": "13:09:58", "direction": "사상"}, {"station": "PSS1012", "arrivalTime": "13:11:30", "departureTime": "13:11:55", "direction": "사상"}, {"station": "PSS1011", "arrivalTime": "13:13:03", "departureTime": "13:13:28", "direction": "사상"}, {"station": "PSS1010", "arrivalTime": "13:14:36", "departureTime": "13:14:56", "direction": "사상"}, {"station": "PSS1009", "arrivalTime": "13:16:25", "departureTime": "13:16:45", "direction": "사상"}, {"station": "PSS1008", "arrivalTime": "13:18:20", "departureTime": "13:18:40", "direction": "사상"}, {"station": "PSS1007", "arrivalTime": "13:19:59", "departureTime": "13:20:29", "direction": "사상"}, {"station": "PSS1006", "arrivalTime": "13:23:00", "departureTime": "13:23:20", "direction": "사상"}, {"station": "PSS1005", "arrivalTime": "13:25:34", "departureTime": "13:25:59", "direction": "사상"}, {"station": "PSS1004", "arrivalTime": "13:28:03", "departureTime": "13:28:38", "direction": "사상"}, {"station": "PSS1003", "arrivalTime": "13:30:11", "departureTime": "13:30:36", "direction": "사상"}, {"station": "PSS1002", "arrivalTime": "13:33:15", "departureTime": "13:33:40", "direction": "사상"}, {"station": "PSS1001", "arrivalTime": "13:35:10", "departureTime": "", "direction": "사상"}], "holiday": [{"station": "PSS1021", "arrivalTime": "", "departureTime": "12:54:42", "direction": "사상"}, {"station": "PSS1020", "arrivalTime": "12:56:39", "departureTime": "12:57:04", "direction": "사상"}, {"station": "PSS1019", "arrivalTime": "12:59:39", "departureTime": "13:00:04", "direction": "사상"}, {"station": "PSS1018", "arrivalTime": "13:01:32", "departureTime": "13:01:57", "direction": "사상"}, {"station": "PSS1017", "arrivalTime": "13:03:06", "departureTime": "13:03:31", "direction": "사상"}, {"station": "PSS1016", "arrivalTime": "13:04:31", "departureTime": "13:04:56", "direction": "사상"}, {"station": "PSS1015", "arrivalTime": "13:06:26", "departureTime": "13:06:51", "direction": "사상"}, {"station": "PSS1014", "arrivalTime": "13:07:48", "departureTime": "13:08:13", "direction": "사상"}, {"station": "PSS1013", "arrivalTime": "13:09:33", "departureTime": "13:09:58", "direction": "사상"}, {"station": "PSS1012", "arrivalTime": "13:11:30", "departureTime": "13:11:55", "direction": "사상"}, {"station": "PSS1011", "arrivalTime": "13:13:03", "departureTime": "13:13:28", "direction": "사상"}, {"station": "PSS1010", "arrivalTime": "13:14:36", "departureTime": "13:14:56", "direction": "사상"}, {"station": "PSS1009", "arrivalTime": "13:16:25", "departureTime": "13:16:45", "direction": "사상"}, {"station": "PSS1008", "arrivalTime": "13:18:20", "departureTime": "13:18:40", "direction": "사상"}, {"station": "PSS1007", "arrivalTime": "13:19:59", "departureTime": "13:20:29", "direction": "사상"}, {"station": "PSS1006", "arrivalTime": "13:23:00", "departureTime": "13:23:20", "direction": "사상"}, {"station": "PSS1005", "arrivalTime": "13:25:34", "departureTime": "13:25:59", "direction": "사상"}, {"station": "PSS1004", "arrivalTime": "13:28:03", "departureTime": "13:28:38", "direction": "사상"}, {"station": "PSS1003", "arrivalTime": "13:30:11", "departureTime": "13:30:36", "direction": "사상"}, {"station": "PSS1002", "arrivalTime": "13:33:15", "departureTime": "13:33:40", "direction": "사상"}, {"station": "PSS1001", "arrivalTime": "13:35:10", "departureTime": "", "direction": "사상"}]}