{"weekday": [{"station": "PSS1021", "arrivalTime": "", "departureTime": "20:29:52", "direction": "사상"}, {"station": "PSS1020", "arrivalTime": "20:31:49", "departureTime": "20:32:14", "direction": "사상"}, {"station": "PSS1019", "arrivalTime": "20:34:49", "departureTime": "20:35:14", "direction": "사상"}, {"station": "PSS1018", "arrivalTime": "20:36:42", "departureTime": "20:37:07", "direction": "사상"}, {"station": "PSS1017", "arrivalTime": "20:38:16", "departureTime": "20:38:41", "direction": "사상"}, {"station": "PSS1016", "arrivalTime": "20:39:41", "departureTime": "20:40:06", "direction": "사상"}, {"station": "PSS1015", "arrivalTime": "20:41:36", "departureTime": "20:42:01", "direction": "사상"}, {"station": "PSS1014", "arrivalTime": "20:42:58", "departureTime": "20:43:23", "direction": "사상"}, {"station": "PSS1013", "arrivalTime": "20:44:43", "departureTime": "20:45:08", "direction": "사상"}, {"station": "PSS1012", "arrivalTime": "20:46:40", "departureTime": "20:47:05", "direction": "사상"}, {"station": "PSS1011", "arrivalTime": "20:48:13", "departureTime": "20:48:38", "direction": "사상"}, {"station": "PSS1010", "arrivalTime": "20:49:46", "departureTime": "20:50:06", "direction": "사상"}, {"station": "PSS1009", "arrivalTime": "20:51:35", "departureTime": "20:51:55", "direction": "사상"}, {"station": "PSS1008", "arrivalTime": "20:53:30", "departureTime": "20:53:50", "direction": "사상"}, {"station": "PSS1007", "arrivalTime": "20:55:09", "departureTime": "20:55:39", "direction": "사상"}, {"station": "PSS1006", "arrivalTime": "20:58:10", "departureTime": "20:58:30", "direction": "사상"}, {"station": "PSS1005", "arrivalTime": "21:00:44", "departureTime": "21:01:09", "direction": "사상"}, {"station": "PSS1004", "arrivalTime": "21:03:13", "departureTime": "21:03:48", "direction": "사상"}, {"station": "PSS1003", "arrivalTime": "21:05:21", "departureTime": "21:05:46", "direction": "사상"}, {"station": "PSS1002", "arrivalTime": "21:08:25", "departureTime": "21:08:50", "direction": "사상"}, {"station": "PSS1001", "arrivalTime": "21:10:20", "departureTime": "", "direction": "사상"}]}