{"weekday": [{"station": "PSS1001", "arrivalTime": "", "departureTime": "08:26:41", "direction": "가야대"}, {"station": "PSS1002", "arrivalTime": "08:27:50", "departureTime": "08:28:15", "direction": "가야대"}, {"station": "PSS1003", "arrivalTime": "08:30:50", "departureTime": "08:31:15", "direction": "가야대"}, {"station": "PSS1004", "arrivalTime": "08:32:47", "departureTime": "08:33:22", "direction": "가야대"}, {"station": "PSS1005", "arrivalTime": "08:35:18", "departureTime": "08:35:43", "direction": "가야대"}, {"station": "PSS1006", "arrivalTime": "08:38:05", "departureTime": "08:38:25", "direction": "가야대"}, {"station": "PSS1007", "arrivalTime": "08:40:52", "departureTime": "08:41:22", "direction": "가야대"}, {"station": "PSS1008", "arrivalTime": "08:42:44", "departureTime": "08:43:04", "direction": "가야대"}, {"station": "PSS1009", "arrivalTime": "08:44:36", "departureTime": "08:44:56", "direction": "가야대"}, {"station": "PSS1010", "arrivalTime": "08:46:24", "departureTime": "08:46:44", "direction": "가야대"}, {"station": "PSS1011", "arrivalTime": "08:47:49", "departureTime": "08:48:14", "direction": "가야대"}, {"station": "PSS1012", "arrivalTime": "08:49:22", "departureTime": "08:49:47", "direction": "가야대"}, {"station": "PSS1013", "arrivalTime": "08:51:19", "departureTime": "08:51:44", "direction": "가야대"}, {"station": "PSS1014", "arrivalTime": "08:53:04", "departureTime": "08:53:29", "direction": "가야대"}, {"station": "PSS1015", "arrivalTime": "08:54:26", "departureTime": "08:54:51", "direction": "가야대"}, {"station": "PSS1016", "arrivalTime": "08:56:19", "departureTime": "08:56:44", "direction": "가야대"}, {"station": "PSS1017", "arrivalTime": "08:57:44", "departureTime": "08:58:09", "direction": "가야대"}, {"station": "PSS1018", "arrivalTime": "08:59:17", "departureTime": "08:59:42", "direction": "가야대"}, {"station": "PSS1019", "arrivalTime": "09:01:10", "departureTime": "09:01:35", "direction": "가야대"}, {"station": "PSS1020", "arrivalTime": "09:04:12", "departureTime": "09:04:37", "direction": "가야대"}, {"station": "PSS1021", "arrivalTime": "09:07:03", "departureTime": "", "direction": "가야대"}]}