{"weekday": [{"station": "PSS201", "arrivalTime": "", "departureTime": "06:16:00", "direction": "양산"}, {"station": "PSS202", "arrivalTime": "06:17:30", "departureTime": "06:17:50", "direction": "양산"}, {"station": "PSS203", "arrivalTime": "06:19:10", "departureTime": "06:19:40", "direction": "양산"}, {"station": "PSS204", "arrivalTime": "06:21:20", "departureTime": "06:21:40", "direction": "양산"}, {"station": "PSS205", "arrivalTime": "06:23:15", "departureTime": "06:23:35", "direction": "양산"}, {"station": "PSS206", "arrivalTime": "06:24:55", "departureTime": "06:25:25", "direction": "양산"}, {"station": "PSS207", "arrivalTime": "06:27:05", "departureTime": "06:27:25", "direction": "양산"}, {"station": "PSS208", "arrivalTime": "06:29:40", "departureTime": "06:30:10", "direction": "양산"}, {"station": "PSS209", "arrivalTime": "06:31:25", "departureTime": "06:31:55", "direction": "양산"}, {"station": "PSS210", "arrivalTime": "06:33:10", "departureTime": "06:33:30", "direction": "양산"}, {"station": "PSS211", "arrivalTime": "06:35:00", "departureTime": "06:35:20", "direction": "양산"}, {"station": "PSS212", "arrivalTime": "06:36:35", "departureTime": "06:37:15", "direction": "양산"}, {"station": "PSS213", "arrivalTime": "06:38:30", "departureTime": "06:38:50", "direction": "양산"}, {"station": "PSS214", "arrivalTime": "06:40:00", "departureTime": "06:40:20", "direction": "양산"}, {"station": "PSS215", "arrivalTime": "06:41:45", "departureTime": "06:42:05", "direction": "양산"}, {"station": "PSS216", "arrivalTime": "06:43:35", "departureTime": "06:43:55", "direction": "양산"}, {"station": "PSS217", "arrivalTime": "06:45:15", "departureTime": "06:45:35", "direction": "양산"}, {"station": "PSS218", "arrivalTime": "06:46:55", "departureTime": "06:47:15", "direction": "양산"}, {"station": "PSS219", "arrivalTime": "06:49:10", "departureTime": "06:50:00", "direction": "양산"}, {"station": "PSS220", "arrivalTime": "06:51:25", "departureTime": "06:51:45", "direction": "양산"}, {"station": "PSS221", "arrivalTime": "06:53:00", "departureTime": "06:53:20", "direction": "양산"}, {"station": "PSS222", "arrivalTime": "06:54:40", "departureTime": "06:55:00", "direction": "양산"}, {"station": "PSS223", "arrivalTime": "06:56:35", "departureTime": "06:56:55", "direction": "양산"}, {"station": "PSS224", "arrivalTime": "06:58:20", "departureTime": "06:58:40", "direction": "양산"}, {"station": "PSS225", "arrivalTime": "07:00:00", "departureTime": "07:00:20", "direction": "양산"}, {"station": "PSS226", "arrivalTime": "07:02:05", "departureTime": "07:02:25", "direction": "양산"}, {"station": "PSS227", "arrivalTime": "07:04:10", "departureTime": "07:04:50", "direction": "양산"}, {"station": "PSS228", "arrivalTime": "07:06:40", "departureTime": "07:07:00", "direction": "양산"}, {"station": "PSS229", "arrivalTime": "07:08:15", "departureTime": "07:08:35", "direction": "양산"}, {"station": "PSS230", "arrivalTime": "07:10:05", "departureTime": "07:10:25", "direction": "양산"}, {"station": "PSS231", "arrivalTime": "07:12:00", "departureTime": "07:12:20", "direction": "양산"}, {"station": "PSS232", "arrivalTime": "07:13:35", "departureTime": "07:13:55", "direction": "양산"}, {"station": "PSS233", "arrivalTime": "07:16:00", "departureTime": "07:16:40", "direction": "양산"}, {"station": "PSS234", "arrivalTime": "07:18:45", "departureTime": "07:19:05", "direction": "양산"}, {"station": "PSS235", "arrivalTime": "07:21:15", "departureTime": "07:21:45", "direction": "양산"}, {"station": "PSS236", "arrivalTime": "07:23:20", "departureTime": "07:23:40", "direction": "양산"}, {"station": "PSS237", "arrivalTime": "07:25:25", "departureTime": "07:25:45", "direction": "양산"}, {"station": "PSS238", "arrivalTime": "07:27:15", "departureTime": "07:27:35", "direction": "양산"}, {"station": "PSS239", "arrivalTime": "07:30:00", "departureTime": "07:30:20", "direction": "양산"}, {"station": "PSS240", "arrivalTime": "07:34:30", "departureTime": "07:34:50", "direction": "양산"}, {"station": "PSS241", "arrivalTime": "07:36:25", "departureTime": "07:36:45", "direction": "양산"}, {"station": "PSS242", "arrivalTime": "07:38:25", "departureTime": "07:38:45", "direction": "양산"}, {"station": "PSS243", "arrivalTime": "07:41:00", "departureTime": "", "direction": "양산"}], "saturday": [{"station": "PSS201", "arrivalTime": "", "departureTime": "06:16:00", "direction": "양산"}, {"station": "PSS202", "arrivalTime": "06:17:30", "departureTime": "06:17:50", "direction": "양산"}, {"station": "PSS203", "arrivalTime": "06:19:10", "departureTime": "06:19:40", "direction": "양산"}, {"station": "PSS204", "arrivalTime": "06:21:20", "departureTime": "06:21:40", "direction": "양산"}, {"station": "PSS205", "arrivalTime": "06:23:15", "departureTime": "06:23:35", "direction": "양산"}, {"station": "PSS206", "arrivalTime": "06:24:55", "departureTime": "06:25:25", "direction": "양산"}, {"station": "PSS207", "arrivalTime": "06:27:05", "departureTime": "06:27:25", "direction": "양산"}, {"station": "PSS208", "arrivalTime": "06:29:40", "departureTime": "06:30:10", "direction": "양산"}, {"station": "PSS209", "arrivalTime": "06:31:25", "departureTime": "06:31:55", "direction": "양산"}, {"station": "PSS210", "arrivalTime": "06:33:10", "departureTime": "06:33:30", "direction": "양산"}, {"station": "PSS211", "arrivalTime": "06:35:00", "departureTime": "06:35:20", "direction": "양산"}, {"station": "PSS212", "arrivalTime": "06:36:35", "departureTime": "06:37:15", "direction": "양산"}, {"station": "PSS213", "arrivalTime": "06:38:30", "departureTime": "06:38:50", "direction": "양산"}, {"station": "PSS214", "arrivalTime": "06:40:00", "departureTime": "06:40:20", "direction": "양산"}, {"station": "PSS215", "arrivalTime": "06:41:45", "departureTime": "06:42:05", "direction": "양산"}, {"station": "PSS216", "arrivalTime": "06:43:35", "departureTime": "06:43:55", "direction": "양산"}, {"station": "PSS217", "arrivalTime": "06:45:15", "departureTime": "06:45:35", "direction": "양산"}, {"station": "PSS218", "arrivalTime": "06:46:55", "departureTime": "06:47:15", "direction": "양산"}, {"station": "PSS219", "arrivalTime": "06:49:10", "departureTime": "06:50:00", "direction": "양산"}, {"station": "PSS220", "arrivalTime": "06:51:25", "departureTime": "06:51:45", "direction": "양산"}, {"station": "PSS221", "arrivalTime": "06:53:00", "departureTime": "06:53:20", "direction": "양산"}, {"station": "PSS222", "arrivalTime": "06:54:40", "departureTime": "06:55:00", "direction": "양산"}, {"station": "PSS223", "arrivalTime": "06:56:35", "departureTime": "06:56:55", "direction": "양산"}, {"station": "PSS224", "arrivalTime": "06:58:20", "departureTime": "06:58:40", "direction": "양산"}, {"station": "PSS225", "arrivalTime": "07:00:00", "departureTime": "07:00:20", "direction": "양산"}, {"station": "PSS226", "arrivalTime": "07:02:05", "departureTime": "07:02:25", "direction": "양산"}, {"station": "PSS227", "arrivalTime": "07:04:10", "departureTime": "07:04:50", "direction": "양산"}, {"station": "PSS228", "arrivalTime": "07:06:40", "departureTime": "07:07:00", "direction": "양산"}, {"station": "PSS229", "arrivalTime": "07:08:15", "departureTime": "07:08:35", "direction": "양산"}, {"station": "PSS230", "arrivalTime": "07:10:05", "departureTime": "07:10:25", "direction": "양산"}, {"station": "PSS231", "arrivalTime": "07:12:00", "departureTime": "07:12:20", "direction": "양산"}, {"station": "PSS232", "arrivalTime": "07:13:35", "departureTime": "07:13:55", "direction": "양산"}, {"station": "PSS233", "arrivalTime": "07:16:00", "departureTime": "07:16:40", "direction": "양산"}, {"station": "PSS234", "arrivalTime": "07:18:45", "departureTime": "07:19:05", "direction": "양산"}, {"station": "PSS235", "arrivalTime": "07:21:15", "departureTime": "07:21:45", "direction": "양산"}, {"station": "PSS236", "arrivalTime": "07:23:20", "departureTime": "07:23:40", "direction": "양산"}, {"station": "PSS237", "arrivalTime": "07:25:25", "departureTime": "07:25:45", "direction": "양산"}, {"station": "PSS238", "arrivalTime": "07:27:15", "departureTime": "07:27:35", "direction": "양산"}, {"station": "PSS239", "arrivalTime": "07:30:00", "departureTime": "07:30:20", "direction": "양산"}, {"station": "PSS240", "arrivalTime": "07:34:30", "departureTime": "07:34:50", "direction": "양산"}, {"station": "PSS241", "arrivalTime": "07:36:25", "departureTime": "07:36:45", "direction": "양산"}, {"station": "PSS242", "arrivalTime": "07:38:25", "departureTime": "07:38:45", "direction": "양산"}, {"station": "PSS243", "arrivalTime": "07:41:00", "departureTime": "", "direction": "양산"}], "holiday": [{"station": "PSS201", "arrivalTime": "", "departureTime": "06:16:00", "direction": "양산"}, {"station": "PSS202", "arrivalTime": "06:17:30", "departureTime": "06:17:50", "direction": "양산"}, {"station": "PSS203", "arrivalTime": "06:19:10", "departureTime": "06:19:40", "direction": "양산"}, {"station": "PSS204", "arrivalTime": "06:21:20", "departureTime": "06:21:40", "direction": "양산"}, {"station": "PSS205", "arrivalTime": "06:23:15", "departureTime": "06:23:35", "direction": "양산"}, {"station": "PSS206", "arrivalTime": "06:24:55", "departureTime": "06:25:25", "direction": "양산"}, {"station": "PSS207", "arrivalTime": "06:27:05", "departureTime": "06:27:25", "direction": "양산"}, {"station": "PSS208", "arrivalTime": "06:29:40", "departureTime": "06:30:10", "direction": "양산"}, {"station": "PSS209", "arrivalTime": "06:31:25", "departureTime": "06:31:55", "direction": "양산"}, {"station": "PSS210", "arrivalTime": "06:33:10", "departureTime": "06:33:30", "direction": "양산"}, {"station": "PSS211", "arrivalTime": "06:35:00", "departureTime": "06:35:20", "direction": "양산"}, {"station": "PSS212", "arrivalTime": "06:36:35", "departureTime": "06:37:15", "direction": "양산"}, {"station": "PSS213", "arrivalTime": "06:38:30", "departureTime": "06:38:50", "direction": "양산"}, {"station": "PSS214", "arrivalTime": "06:40:00", "departureTime": "06:40:20", "direction": "양산"}, {"station": "PSS215", "arrivalTime": "06:41:45", "departureTime": "06:42:05", "direction": "양산"}, {"station": "PSS216", "arrivalTime": "06:43:35", "departureTime": "06:43:55", "direction": "양산"}, {"station": "PSS217", "arrivalTime": "06:45:15", "departureTime": "06:45:35", "direction": "양산"}, {"station": "PSS218", "arrivalTime": "06:46:55", "departureTime": "06:47:15", "direction": "양산"}, {"station": "PSS219", "arrivalTime": "06:49:10", "departureTime": "06:50:00", "direction": "양산"}, {"station": "PSS220", "arrivalTime": "06:51:25", "departureTime": "06:51:45", "direction": "양산"}, {"station": "PSS221", "arrivalTime": "06:53:00", "departureTime": "06:53:20", "direction": "양산"}, {"station": "PSS222", "arrivalTime": "06:54:40", "departureTime": "06:55:00", "direction": "양산"}, {"station": "PSS223", "arrivalTime": "06:56:35", "departureTime": "06:56:55", "direction": "양산"}, {"station": "PSS224", "arrivalTime": "06:58:20", "departureTime": "06:58:40", "direction": "양산"}, {"station": "PSS225", "arrivalTime": "07:00:00", "departureTime": "07:00:20", "direction": "양산"}, {"station": "PSS226", "arrivalTime": "07:02:05", "departureTime": "07:02:25", "direction": "양산"}, {"station": "PSS227", "arrivalTime": "07:04:10", "departureTime": "07:04:50", "direction": "양산"}, {"station": "PSS228", "arrivalTime": "07:06:40", "departureTime": "07:07:00", "direction": "양산"}, {"station": "PSS229", "arrivalTime": "07:08:15", "departureTime": "07:08:35", "direction": "양산"}, {"station": "PSS230", "arrivalTime": "07:10:05", "departureTime": "07:10:25", "direction": "양산"}, {"station": "PSS231", "arrivalTime": "07:12:00", "departureTime": "07:12:20", "direction": "양산"}, {"station": "PSS232", "arrivalTime": "07:13:35", "departureTime": "07:13:55", "direction": "양산"}, {"station": "PSS233", "arrivalTime": "07:16:00", "departureTime": "07:16:40", "direction": "양산"}, {"station": "PSS234", "arrivalTime": "07:18:45", "departureTime": "07:19:05", "direction": "양산"}, {"station": "PSS235", "arrivalTime": "07:21:15", "departureTime": "07:21:45", "direction": "양산"}, {"station": "PSS236", "arrivalTime": "07:23:20", "departureTime": "07:23:40", "direction": "양산"}, {"station": "PSS237", "arrivalTime": "07:25:25", "departureTime": "07:25:45", "direction": "양산"}, {"station": "PSS238", "arrivalTime": "07:27:15", "departureTime": "07:27:35", "direction": "양산"}, {"station": "PSS239", "arrivalTime": "07:30:00", "departureTime": "07:30:20", "direction": "양산"}, {"station": "PSS240", "arrivalTime": "07:34:30", "departureTime": "07:34:50", "direction": "양산"}, {"station": "PSS241", "arrivalTime": "07:36:25", "departureTime": "07:36:45", "direction": "양산"}, {"station": "PSS242", "arrivalTime": "07:38:25", "departureTime": "07:38:45", "direction": "양산"}, {"station": "PSS243", "arrivalTime": "07:41:00", "departureTime": "", "direction": "양산"}]}