{"weekday": [{"station": "PSS401", "arrivalTime": "", "departureTime": "15:57:00", "direction": "안평"}, {"station": "PSS402", "arrivalTime": "15:58:45", "departureTime": "15:59:20", "direction": "안평"}, {"station": "PSS403", "arrivalTime": "16:00:30", "departureTime": "16:01:00", "direction": "안평"}, {"station": "PSS404", "arrivalTime": "16:02:10", "departureTime": "16:02:30", "direction": "안평"}, {"station": "PSS405", "arrivalTime": "16:03:50", "departureTime": "16:04:15", "direction": "안평"}, {"station": "PSS406", "arrivalTime": "16:05:30", "departureTime": "16:05:55", "direction": "안평"}, {"station": "PSS407", "arrivalTime": "16:07:50", "departureTime": "16:08:15", "direction": "안평"}, {"station": "PSS408", "arrivalTime": "16:09:35", "departureTime": "16:09:55", "direction": "안평"}, {"station": "PSS409", "arrivalTime": "16:11:15", "departureTime": "16:11:35", "direction": "안평"}, {"station": "PSS410", "arrivalTime": "16:13:20", "departureTime": "16:13:40", "direction": "안평"}, {"station": "PSS411", "arrivalTime": "16:15:45", "departureTime": "16:16:15", "direction": "안평"}, {"station": "PSS412", "arrivalTime": "16:18:00", "departureTime": "16:18:30", "direction": "안평"}, {"station": "PSS413", "arrivalTime": "16:19:55", "departureTime": "16:20:15", "direction": "안평"}, {"station": "PSS414", "arrivalTime": "16:22:00", "departureTime": "", "direction": "안평"}], "saturday": [{"station": "PSS401", "arrivalTime": "", "departureTime": "16:31:30", "direction": "안평"}, {"station": "PSS402", "arrivalTime": "16:33:15", "departureTime": "16:33:50", "direction": "안평"}, {"station": "PSS403", "arrivalTime": "16:35:00", "departureTime": "16:35:30", "direction": "안평"}, {"station": "PSS404", "arrivalTime": "16:36:40", "departureTime": "16:37:00", "direction": "안평"}, {"station": "PSS405", "arrivalTime": "16:38:20", "departureTime": "16:38:45", "direction": "안평"}, {"station": "PSS406", "arrivalTime": "16:40:00", "departureTime": "16:40:25", "direction": "안평"}, {"station": "PSS407", "arrivalTime": "16:42:20", "departureTime": "16:42:45", "direction": "안평"}, {"station": "PSS408", "arrivalTime": "16:44:05", "departureTime": "16:44:25", "direction": "안평"}, {"station": "PSS409", "arrivalTime": "16:45:45", "departureTime": "16:46:05", "direction": "안평"}, {"station": "PSS410", "arrivalTime": "16:47:50", "departureTime": "16:48:10", "direction": "안평"}, {"station": "PSS411", "arrivalTime": "16:50:15", "departureTime": "16:50:45", "direction": "안평"}, {"station": "PSS412", "arrivalTime": "16:52:30", "departureTime": "16:53:00", "direction": "안평"}, {"station": "PSS413", "arrivalTime": "16:54:25", "departureTime": "16:54:45", "direction": "안평"}, {"station": "PSS414", "arrivalTime": "16:56:30", "departureTime": "", "direction": "안평"}], "holiday": [{"station": "PSS401", "arrivalTime": "", "departureTime": "17:13:00", "direction": "안평"}, {"station": "PSS402", "arrivalTime": "17:14:45", "departureTime": "17:15:20", "direction": "안평"}, {"station": "PSS403", "arrivalTime": "17:16:30", "departureTime": "17:17:00", "direction": "안평"}, {"station": "PSS404", "arrivalTime": "17:18:10", "departureTime": "17:18:30", "direction": "안평"}, {"station": "PSS405", "arrivalTime": "17:19:50", "departureTime": "17:20:15", "direction": "안평"}, {"station": "PSS406", "arrivalTime": "17:21:30", "departureTime": "17:21:55", "direction": "안평"}, {"station": "PSS407", "arrivalTime": "17:23:50", "departureTime": "17:24:15", "direction": "안평"}, {"station": "PSS408", "arrivalTime": "17:25:35", "departureTime": "17:25:55", "direction": "안평"}, {"station": "PSS409", "arrivalTime": "17:27:15", "departureTime": "17:27:35", "direction": "안평"}, {"station": "PSS410", "arrivalTime": "17:29:20", "departureTime": "17:29:40", "direction": "안평"}, {"station": "PSS411", "arrivalTime": "17:31:45", "departureTime": "17:32:15", "direction": "안평"}, {"station": "PSS412", "arrivalTime": "17:34:00", "departureTime": "17:34:30", "direction": "안평"}, {"station": "PSS413", "arrivalTime": "17:35:55", "departureTime": "17:36:15", "direction": "안평"}, {"station": "PSS414", "arrivalTime": "17:38:00", "departureTime": "", "direction": "안평"}]}